easygraphs/__init__.py
easygraphs/global_context.py
easygraphs/data_analyzer/__init__.py
easygraphs/data_analyzer/classifiers.py
easygraphs/data_analyzer/data_utils.py
easygraphs/data_analyzer/feature_analyzer.py
easygraphs/data_analyzer/table_loader.py
easygraphs/graph_analyzer/__init__.py
easygraphs/graph_analyzer/attribute_analyzer.py
easygraphs/graph_analyzer/cross_associations_analyzer.py
easygraphs/graph_analyzer/dos_analyzer.py
easygraphs/graph_analyzer/focusco_analyzer.py
easygraphs/graph_analyzer/fraudar_analyzer.py
easygraphs/graph_analyzer/graph_visualizer.py
easygraphs/graph_analyzer/network_analyzer.py
easygraphs/graph_analyzer/paican_analyzer.py
easygraphs/graph_analyzer/radar_analyzer.py
easygraphs/graph_analyzer/specgreedy_analyzer.py
easygraphs/graph_analyzer/spectral_analyzer.py
easygraphs/utils/BPE.py
easygraphs/utils/__init__.py
easygraphs/utils/collection.py
easygraphs/utils/dataset.py
easygraphs/utils/evaluate_utils.py
easygraphs/utils/graph.py
easygraphs/utils/graph_generator.py
easygraphs/utils/graph_loader.py
easygraphs/utils/graph_ops.py
easygraphs/utils/graph_utils.py
easygraphs/utils/io_utils.py
easygraphs/utils/math.py
easygraphs/utils/timer.py
easygraphs/utils/utils.py
easygraphs/utils/plot_utils/__init__.py
easygraphs/utils/plot_utils/basic_plot_utils.py
easygraphs/utils/plot_utils/graph_plot_utils.py
easygraphs/utils/plot_utils/matrix_vis_utils.py
easygraphs/utils/plot_utils/plot_heatmap.py
easygraphs/utils/plot_utils/plot_utils.py
easygraphs-0.6.0.dist-info/LICENSE
easygraphs-0.6.0.dist-info/METADATA
easygraphs-0.6.0.dist-info/WHEEL
easygraphs-0.6.0.dist-info/top_level.txt
easygraphs-0.6.0.dist-info/RECORD
