Metadata-Version: 2.1
Name: easygraphs
Version: 0.6.0
Summary: A library for graph analysis, graph embedding and graph anomaly detection
Home-page: https://github.com/EndlessLethe/easygraphs
Author: EndlessLethe
Author-email: zengsw_study@qq.com
License: UNKNOWN
Keywords: graph analysis anomaly detection
Platform: UNKNOWN
Requires-Python: >=3
Requires-Dist: matplotlib (>=3.2.2scipy>=1.5.0)
Requires-Dist: numpy (>=1.17.0)
Requires-Dist: plotly (>=4.9.0)
Requires-Dist: seaborn (>=0.11.1)
Requires-Dist: requests (>=2.24.0)
Requires-Dist: pandas (>=1.0.5)
Requires-Dist: networkx (>=2.4)
Requires-Dist: dgl (>=0.6.1)
Requires-Dist: scikit-learn (>=0.24.2)
